[{"IDDPTO":"01","DEPARTAMEN":"AMAZONAS","CAPITAL":"CHACHAPOYAS","FUENTE":"INEI"},{"IDDPTO":"02","DEPARTAMEN":"ANCASH","CAPITAL":"HUARAZ","FUENTE":"INEI"},{"IDDPTO":"03","DEPARTAMEN":"APURIMAC","CAPITAL":"ABANCAY","FUENTE":"INEI"},{"IDDPTO":"04","DEPARTAMEN":"AREQUIPA","CAPITAL":"AREQUIPA","FUENTE":"INEI"},{"IDDPTO":"05","DEPARTAMEN":"AYACUCHO","CAPITAL":"AYACUCHO","FUENTE":"INEI"},{"IDDPTO":"06","DEPARTAMEN":"CAJAMARCA","CAPITAL":"CAJAMARCA","FUENTE":"INEI"},{"IDDPTO":"07","DEPARTAMEN":"CALLAO","CAPITAL":"CALLAO","FUENTE":"INEI"},{"IDDPTO":"08","DEPARTAMEN":"CUSCO","CAPITAL":"CUSCO","FUENTE":"INEI"},{"IDDPTO":"09","DEPARTAMEN":"HUANCAVELICA","CAPITAL":"HUANCAVELICA","FUENTE":"INEI"},{"IDDPTO":"10","DEPARTAMEN":"HUANUCO","CAPITAL":"HUANUCO","FUENTE":"INEI"},{"IDDPTO":"11","DEPARTAMEN":"ICA","CAPITAL":"ICA","FUENTE":"INEI"},{"IDDPTO":"12","DEPARTAMEN":"JUNIN","CAPITAL":"HUANCAYO","FUENTE":"INEI"},{"IDDPTO":"13","DEPARTAMEN":"LA LIBERTAD","CAPITAL":"TRUJILLO","FUENTE":"INEI"},{"IDDPTO":"14","DEPARTAMEN":"LAMBAYEQUE","CAPITAL":"CHICLAYO","FUENTE":"INEI"},{"IDDPTO":"15","DEPARTAMEN":"LIMA","CAPITAL":"LIMA","FUENTE":"INEI"},{"IDDPTO":"16","DEPARTAMEN":"LORETO","CAPITAL":"IQUITOS","FUENTE":"INEI"},{"IDDPTO":"17","DEPARTAMEN":"MADRE DE DIOS","CAPITAL":"PUERTO MALDONADO","FUENTE":"INEI"},{"IDDPTO":"18","DEPARTAMEN":"MOQUEGUA","CAPITAL":"MOQUEGUA","FUENTE":"INEI"},{"IDDPTO":"19","DEPARTAMEN":"PASCO","CAPITAL":"CERRO DE PASCO","FUENTE":"INEI"},{"IDDPTO":"20","DEPARTAMEN":"PIURA","CAPITAL":"PIURA","FUENTE":"INEI"},{"IDDPTO":"21","DEPARTAMEN":"PUNO","CAPITAL":"PUNO","FUENTE":"INEI"},{"IDDPTO":"22","DEPARTAMEN":"SAN MARTIN","CAPITAL":"MOYOBAMBA","FUENTE":"INEI"},{"IDDPTO":"23","DEPARTAMEN":"TACNA","CAPITAL":"TACNA","FUENTE":"INEI"},{"IDDPTO":"24","DEPARTAMEN":"TUMBES","CAPITAL":"TUMBES","FUENTE":"INEI"},{"IDDPTO":"25","DEPARTAMEN":"UCAYALI","CAPITAL":"PUCALLPA","FUENTE":"INEI"}]